create_pattern/__init__.py
create_pattern-1.0.0.dist-info/LICENCE
create_pattern-1.0.0.dist-info/METADATA
create_pattern-1.0.0.dist-info/WHEEL
create_pattern-1.0.0.dist-info/top_level.txt
create_pattern-1.0.0.dist-info/RECORD
