Metadata-Version: 2.1
Name: create-pattern
Version: 1.0.0
Summary: This package can create Patterns in all A to Z shapes and many more patterns ...
Home-page: UNKNOWN
Author: Akshat Tiwari
Author-email: thealphacoding@gmail.com
License: UNKNOWN
Platform: UNKNOWN
Classifier: Programming Language :: Python :: 3
Classifier: License :: OSI Approved :: MIT License
Classifier: Operating System :: OS Independent
Requires-Python: >=3.0
